segmentation/__init__.py
segmentation/dataset.py
segmentation/model.py
segmentation/modules.py
segmentation/network.py
segmentation/optimizer.py
segmentation/settings.py
segmentation/util.py
segmentation/gui/__init__.py
segmentation/gui/gui.py
segmentation/gui/xml_util.py
segmentation/postprocessing/__init__.py
segmentation/postprocessing/baseline_extraction.py
segmentation/postprocessing/baseline_postprocess_by_borders.py
segmentation/postprocessing/simplify_line.py
segmentation/postprocessing/text_border_estimation.py
segmentation/preprocessing/__init__.py
segmentation/preprocessing/basic_binarizer.py
segmentation/preprocessing/ocrupus.py
segmentation/scripts/__init__.py
segmentation/scripts/image_map.py
segmentation/scripts/predict.py
segmentation/scripts/train.py
torch_pixel_classifier-0.1.data/data/requirements.txt
torch_pixel_classifier-0.1.dist-info/LICENSE.md
torch_pixel_classifier-0.1.dist-info/METADATA
torch_pixel_classifier-0.1.dist-info/WHEEL
torch_pixel_classifier-0.1.dist-info/top_level.txt
torch_pixel_classifier-0.1.dist-info/RECORD
