Metadata-Version: 2.1
Name: torch-pixel-classifier
Version: 0.1
Summary: UNKNOWN
Home-page: https://github.com/Gawajn/segmentation-pytorch
Author: Alexander Hartelt
Author-email: alexander.hartelt@informatik.uni-wuerzburg.de
License: UNKNOWN
Keywords: OCR,page segmentation,pixel classifier
Platform: UNKNOWN
Classifier: Programming Language :: Python :: 3
Classifier: License :: OSI Approved :: GNU General Public License v3 or later (GPLv3+)
Classifier: License :: OSI Approved :: Apache Software License
Classifier: Intended Audience :: Science/Research
Classifier: Topic :: Scientific/Engineering :: Image Recognition
Requires-Dist: segmentation-models-pytorch
Requires-Dist: torch (~=1.5.0)
Requires-Dist: PageXML-to-Mask-converter
Requires-Dist: torchvision
Requires-Dist: pillow (~=6.2.1)
Requires-Dist: numpy (~=1.17.4)
Requires-Dist: ttach
Requires-Dist: setuptools (~=41.6.0)
Requires-Dist: matplotlib (~=3.1.1)
Requires-Dist: pandas (~=0.25.3)
Requires-Dist: seaborn (~=0.9.0)
Requires-Dist: tqdm (~=4.38.0)
Requires-Dist: albumentations (~=0.4.2)
Requires-Dist: scikit-image (~=0.16.2)
Requires-Dist: opencv-python
Requires-Dist: sklearn
